BnpInstaller/BnpInstaller.py
BnpInstaller/__init__.py
BnpInstaller-1.0.4.dist-info/LICENSE
BnpInstaller-1.0.4.dist-info/METADATA
BnpInstaller-1.0.4.dist-info/WHEEL
BnpInstaller-1.0.4.dist-info/entry_points.txt
BnpInstaller-1.0.4.dist-info/top_level.txt
BnpInstaller-1.0.4.dist-info/RECORD
