Metadata-Version: 2.1
Name: BnpInstaller
Version: 1.0.4
Summary: A simple CLI app to install bnp mods.
Home-page: https://github.com/ArchLeaders/BnpInstaller
Author: ArchLeaders
Author-email: archleadership28@gmail.com
License: UNKNOWN
Platform: UNKNOWN
Classifier: License :: OSI Approved :: MIT License
Classifier: Operating System :: OS Independent
Classifier: Programming Language :: Python :: 3 :: Only
Requires-Python: >=3.7
License-File: LICENSE
Requires-Dist: bcml (>=3.0.0)
